cglbtest/__init__.py
cglbtest/assets_mgmt.py
cglbtest/cli.py
cglbtest/env.py
cglbtest/exceptions.py
cglbtest/file_reader_csv.py
cglbtest/file_reader_img.py
cglbtest/file_reader_interface.py
cglbtest/file_reader_manager.py
cglbtest/file_reader_nc.py
cglbtest/file_reader_txt.py
cglbtest/process_compare.py
cglbtest/process_execute_and_compare.py
cglbtest/utils_compare.py
cglbtest/utils_compare_imgs.py
cglbtest/utils_compare_report.html
cglbtest/utils_compare_report.py
cglbtest/utils_compare_report_anim.js
cglbtest/utils_compare_report_chartlibs_echarts.js
cglbtest/utils_compare_report_chartlibs_plotly.js
cglbtest/utils_compare_report_curves.js
cglbtest/utils_compare_report_dom.js
cglbtest/utils_compare_report_framesseries.js
cglbtest/utils_compare_report_palette.js
cglbtest/utils_compare_values.py
cglbtest/utils_default_logo_src.py
cglbtest/utils_execute.py
cglbtest/utils_file copy.py
cglbtest/utils_file.py
cglbtest/utils_template.py
cglbtest-0.1.4.dist-info/METADATA
cglbtest-0.1.4.dist-info/WHEEL
cglbtest-0.1.4.dist-info/entry_points.txt
cglbtest-0.1.4.dist-info/RECORD
