Metadata-Version: 2.1
Name: cglbtest
Version: 0.1.4
Summary: cglbtest Framework
Home-page: https://cesgenslab.cloud/
Author: CesGensLaB
Author-email: contact@cesgenlab.fr
Requires-Python: >=3.11,<4.0
Classifier: Programming Language :: Python :: 3
Classifier: Programming Language :: Python :: 3.11
Classifier: Programming Language :: Python :: 3.12
Requires-Dist: click (>=8.1.7,<9.0.0)
Requires-Dist: coloredlogs (>=15.0.1,<16.0.0)
Requires-Dist: jinja2 (>=3.1.4,<4.0.0)
Requires-Dist: netcdf4 (>=1.7.2,<2.0.0)
Requires-Dist: opencv-python (>=4.10.0.84,<5.0.0.0)
Requires-Dist: pyyaml (>=6.0.2,<7.0.0)
